<item>
	<title>Lunchtime fun</title>
	<link>http://homefornow.us/lunchtime-fun</link>
	<pubDate>Fri Oct 12 17:59:07 -0700 2012</pubDate>
	
	<dc:creator><![CDATA[Morgan Estes]]></dc:creator>
	
	

	<category><![CDATA[Uncategorized]]></category>

	<category domain="category" nicename="uncategorized"><![CDATA[Uncategorized]]></category>

  <guid isPermaLink="false">http://homefornow.us/lunchtime-fun</guid>
	<description></description>
	<content:encoded><![CDATA[<p><div class='p_embed p_image_embed'>
<a href="http://getfile0.posterous.com/getfile/files.posterous.com/homefornow/ngeghFbzjHqHqJigAFxyflewexnJujaAcBmqkzjbavGricHaasHnbDoiHkDn/-2012816218.jpg"><img alt="-2012816218" src="http://getfile0.posterous.com/getfile/files.posterous.com/homefornow/ngeghFbzjHqHqJigAFxyflewexnJujaAcBmqkzjbavGricHaasHnbDoiHkDn/-2012816218.jpg" /></a>
<a href="http://getfile1.posterous.com/getfile/files.posterous.com/homefornow/sErAFjwDnfEJibGFzsmyhFynyIJmofCrdJHifFzmyJuldJludjgJBagBdiqD/-2088232893.jpg"><img alt="-2088232893" src="http://getfile1.posterous.com/getfile/files.posterous.com/homefornow/sErAFjwDnfEJibGFzsmyhFynyIJmofCrdJHifFzmyJuldJludjgJBagBdiqD/-2088232893.jpg" /></a>
</div>
</p>Jessica had the day off for Fall Break, so she and Joanna trekked out to Long John Silver's for lunch -- where I happily joined them. <p>Joanna got to taste greasy chicken and greasy fish, and seemed to enjoy both. We definitely won't make this a habit for her, as we're trying to break ourselves of bad eating habits. </p><p>But for today, it made J a happy girl!</p>]]></content:encoded>
	<excerpt:encoded><![CDATA[Jessica had the day off for Fall Break, so she and Joanna trekked out to Long John Silver's for lunch -- where I happily joined them. Joanna got to taste greasy chicken and greasy fish, and seemed to enjoy both. We definitely won't make this a hab...]]></excerpt:encoded>	

	<wp:post_date>Fri Oct 12 17:59:07 -0700 2012</wp:post_date>
	<wp:post_date_gmt>Fri Oct 12 17:59:07 -0700 2012</wp:post_date_gmt>
	<wp:comment_status>open</wp:comment_status>
	<wp:ping_status>open</wp:ping_status>
	<wp:post_id>165033696</wp:post_id>
	<wp:post_name>lunchtime-fun</wp:post_name>
	<wp:status>publish</wp:status>
	<wp:post_parent>0</wp:post_parent>
	<wp:menu_order>0</wp:menu_order>
	<wp:post_type>post</wp:post_type>
	<wp:post_password></wp:post_password>
	<wp:is_sticky>0</wp:is_sticky>

	
</item>
